[
  {
    "name": "Rations, Fresh",
    "type": "Item",
    "data": {
      "name": "Rations, Fresh",
      "equip": "Pack",
      "carried": "Pack",
      "slots": 1,
      "cost": "Ob 1",
      "description": "",
      "capacity": 0,
      "bundleSize": 2,
      "resizes": false,
      "maxDraughts": 0,
      "draughts": 0,
      "liquid": "",
      "consumable": {
        "consumes": "self",
        "icon": "fa-drumstick-bite",
        "iconStyle": "color:#cc8820"
      },
      "equipOptions": {
        "option1": {
          "value": "Pack"
        },
        "option2": {
          "value": ""
        },
        "option3": {
          "value": ""
        }
      },
      "carryOptions": {
        "option1": {
          "value": "Pack"
        },
        "option2": {
          "value": ""
        },
        "option3": {
          "value": ""
        }
      },
      "slotOptions": {
        "option1": {
          "value": 1
        },
        "option2": {
          "value": 0
        },
        "option3": {
          "value": 0
        }
      },
      "notes": ""
    }
  },
  {
    "name": "Rations, Preserved",
    "type": "Item",
    "data": {
      "name": "Rations, Preserved",
      "equip": "Pack",
      "carried": "Pack",
      "slots": 1,
      "cost": "Ob 2",
      "description": "",
      "capacity": 0,
      "bundleSize": 3,
      "resizes": false,
      "maxDraughts": 0,
      "draughts": 0,
      "liquid": "",
      "consumable": {
        "consumes": "self",
        "icon": "fa-drumstick-bite",
        "iconStyle": "color:#cc8820"
      },
      "equipOptions": {
        "option1": {
          "value": "Pack"
        },
        "option2": {
          "value": ""
        },
        "option3": {
          "value": ""
        }
      },
      "carryOptions": {
        "option1": {
          "value": "Pack"
        },
        "option2": {
          "value": ""
        },
        "option3": {
          "value": ""
        }
      },
      "slotOptions": {
        "option1": {
          "value": 1
        },
        "option2": {
          "value": 0
        },
        "option3": {
          "value": 0
        }
      },
      "notes": ""
    }
  }
]
